py_change_code/__init__.py
py_change_code-0.1.0.dist-info/METADATA
py_change_code-0.1.0.dist-info/RECORD
py_change_code-0.1.0.dist-info/WHEEL
py_change_code-0.1.0.dist-info/top_level.txt
